{
  "appInfo" : {
    "build" : "212.4746.92",
    "buildDate" : "2021-07-27T07:08:35.548Z[UTC]",
    "productCode" : "IC",
    "generated" : "2022-11-08T08:08:56.539421Z",
    "os" : "macOS 11.5",
    "runtime" : "JetBrains s.r.o. 11.0.11 11.0.11+9-b1504.13"
  },
  "runtimeInfo" : {
    "maxMemory" : 536870912,
    "numberOfProcessors" : 12,
    "maxNumberOfIndexingThreads" : 4,
    "maxSizeOfFileForIntelliSense" : 2560000,
    "maxSizeOfFileForContentLoading" : 20971520
  },
  "projectIndexingHistory" : {
    "projectName" : "demo",
    "times" : {
      "indexingReason" : "Project roots have changed",
      "totalUpdatingTime" : 3592484426,
      "indexingTime" : 0,
      "contentLoadingTime" : 0,
      "scanFilesTime" : 3521832000,
      "pushPropertiesTime" : 2619000,
      "indexExtensionsTime" : 0,
      "updatingStart" : "2022-11-08T08:08:52.939158Z",
      "updatingEnd" : "2022-11-08T08:08:56.532942Z",
      "totalSuspendedTime" : 0,
      "wasInterrupted" : false
    },
    "fileCount" : {
      "numberOfFileProviders" : 75,
      "numberOfScannedFiles" : 70236,
      "numberOfFilesIndexedByInfrastructureExtensionsDuringScan" : 0,
      "numberOfFilesScheduledForIndexingAfterScan" : 0,
      "numberOfFilesIndexedByInfrastructureExtensionsDuringIndexingStage" : 0,
      "numberOfFilesIndexedWithLoadingContent" : 0
    },
    "totalStatsPerFileType" : [ ],
    "totalStatsPerIndexer" : [ ],
    "scanningStatistics" : [ {
      "providerName" : "JDK 1.8",
      "numberOfScannedFiles" : 52131,
      "numberOfSkippedFiles" : 0,
      "numberOfFilesForIndexing" : 0,
      "numberOfFilesFullyIndexedByInfrastructureExtensions" : 0,
      "scanningTime" : 1522716011,
      "timeProcessingUpToDateFiles" : 0,
      "timeUpdatingContentLessIndexes" : 77749179,
      "timeIndexingWithoutContent" : 0
    }, {
      "providerName" : "Library Maven: org.apache.hadoop:hadoop-common:2.8.5",
      "numberOfScannedFiles" : 2278,
      "numberOfSkippedFiles" : 0,
      "numberOfFilesForIndexing" : 0,
      "numberOfFilesFullyIndexedByInfrastructureExtensions" : 0,
      "scanningTime" : 819504152,
      "timeProcessingUpToDateFiles" : 0,
      "timeUpdatingContentLessIndexes" : 10324484,
      "timeIndexingWithoutContent" : 0
    }, {
      "providerName" : "Library Maven: com.google.guava:guava:11.0.2",
      "numberOfScannedFiles" : 1269,
      "numberOfSkippedFiles" : 0,
      "numberOfFilesForIndexing" : 0,
      "numberOfFilesFullyIndexedByInfrastructureExtensions" : 0,
      "scanningTime" : 673571807,
      "timeProcessingUpToDateFiles" : 0,
      "timeUpdatingContentLessIndexes" : 6983692,
      "timeIndexingWithoutContent" : 0
    }, {
      "providerName" : "Library Maven: org.apache.commons:commons-math3:3.1.1",
      "numberOfScannedFiles" : 961,
      "numberOfSkippedFiles" : 0,
      "numberOfFilesForIndexing" : 0,
      "numberOfFilesFullyIndexedByInfrastructureExtensions" : 0,
      "scanningTime" : 611436163,
      "timeProcessingUpToDateFiles" : 0,
      "timeUpdatingContentLessIndexes" : 4959215,
      "timeIndexingWithoutContent" : 0
    }, {
      "providerName" : "Library Maven: commons-collections:commons-collections:3.2.2",
      "numberOfScannedFiles" : 754,
      "numberOfSkippedFiles" : 0,
      "numberOfFilesForIndexing" : 0,
      "numberOfFilesFullyIndexedByInfrastructureExtensions" : 0,
      "scanningTime" : 437728203,
      "timeProcessingUpToDateFiles" : 0,
      "timeUpdatingContentLessIndexes" : 3659482,
      "timeIndexingWithoutContent" : 0
    }, {
      "providerName" : "Library Maven: org.apache.httpcomponents:httpclient:4.5.2",
      "numberOfScannedFiles" : 471,
      "numberOfSkippedFiles" : 0,
      "numberOfFilesForIndexing" : 0,
      "numberOfFilesFullyIndexedByInfrastructureExtensions" : 0,
      "scanningTime" : 300788083,
      "timeProcessingUpToDateFiles" : 0,
      "timeUpdatingContentLessIndexes" : 3629204,
      "timeIndexingWithoutContent" : 0
    }, {
      "providerName" : "Library Maven: org.apache.httpcomponents:httpcore:4.4.4",
      "numberOfScannedFiles" : 261,
      "numberOfSkippedFiles" : 0,
      "numberOfFilesForIndexing" : 0,
      "numberOfFilesFullyIndexedByInfrastructureExtensions" : 0,
      "scanningTime" : 260601182,
      "timeProcessingUpToDateFiles" : 0,
      "timeUpdatingContentLessIndexes" : 17151768,
      "timeIndexingWithoutContent" : 0
    }, {
      "providerName" : "Library Maven: com.sun.xml.bind:jaxb-impl:2.2.3-1",
      "numberOfScannedFiles" : 673,
      "numberOfSkippedFiles" : 0,
      "numberOfFilesForIndexing" : 0,
      "numberOfFilesFullyIndexedByInfrastructureExtensions" : 0,
      "scanningTime" : 254423599,
      "timeProcessingUpToDateFiles" : 0,
      "timeUpdatingContentLessIndexes" : 2741355,
      "timeIndexingWithoutContent" : 0
    }, {
      "providerName" : "Library Maven: org.codehaus.jackson:jackson-mapper-asl:1.9.13",
      "numberOfScannedFiles" : 507,
      "numberOfSkippedFiles" : 0,
      "numberOfFilesForIndexing" : 0,
      "numberOfFilesFullyIndexedByInfrastructureExtensions" : 0,
      "scanningTime" : 251142851,
      "timeProcessingUpToDateFiles" : 0,
      "timeUpdatingContentLessIndexes" : 2036113,
      "timeIndexingWithoutContent" : 0
    }, {
      "providerName" : "Library Maven: com.sun.jersey:jersey-server:1.9",
      "numberOfScannedFiles" : 557,
      "numberOfSkippedFiles" : 0,
      "numberOfFilesForIndexing" : 0,
      "numberOfFilesFullyIndexedByInfrastructureExtensions" : 0,
      "scanningTime" : 237547112,
      "timeProcessingUpToDateFiles" : 0,
      "timeUpdatingContentLessIndexes" : 2286436,
      "timeIndexingWithoutContent" : 0
    }, {
      "providerName" : "Library Maven: bigboot:jindofs:3.7.3",
      "numberOfScannedFiles" : 2405,
      "numberOfSkippedFiles" : 0,
      "numberOfFilesForIndexing" : 0,
      "numberOfFilesFullyIndexedByInfrastructureExtensions" : 0,
      "scanningTime" : 217198375,
      "timeProcessingUpToDateFiles" : 0,
      "timeUpdatingContentLessIndexes" : 7377181,
      "timeIndexingWithoutContent" : 0
    }, {
      "providerName" : "Module 'demo'",
      "numberOfScannedFiles" : 22,
      "numberOfSkippedFiles" : 0,
      "numberOfFilesForIndexing" : 0,
      "numberOfFilesFullyIndexedByInfrastructureExtensions" : 0,
      "scanningTime" : 193402920,
      "timeProcessingUpToDateFiles" : 0,
      "timeUpdatingContentLessIndexes" : 7153817,
      "timeIndexingWithoutContent" : 0
    }, {
      "providerName" : "Library Maven: org.apache.htrace:htrace-core4:4.0.1-incubating",
      "numberOfScannedFiles" : 767,
      "numberOfSkippedFiles" : 0,
      "numberOfFilesForIndexing" : 0,
      "numberOfFilesFullyIndexedByInfrastructureExtensions" : 0,
      "scanningTime" : 139437303,
      "timeProcessingUpToDateFiles" : 0,
      "timeUpdatingContentLessIndexes" : 2881155,
      "timeIndexingWithoutContent" : 0
    }, {
      "providerName" : "Library Maven: org.apache.avro:avro:1.7.4",
      "numberOfScannedFiles" : 215,
      "numberOfSkippedFiles" : 0,
      "numberOfFilesForIndexing" : 0,
      "numberOfFilesFullyIndexedByInfrastructureExtensions" : 0,
      "scanningTime" : 139267413,
      "timeProcessingUpToDateFiles" : 0,
      "timeUpdatingContentLessIndexes" : 799799,
      "timeIndexingWithoutContent" : 0
    }, {
      "providerName" : "Library Maven: commons-io:commons-io:2.4",
      "numberOfScannedFiles" : 115,
      "numberOfSkippedFiles" : 0,
      "numberOfFilesForIndexing" : 0,
      "numberOfFilesFullyIndexedByInfrastructureExtensions" : 0,
      "scanningTime" : 136986128,
      "timeProcessingUpToDateFiles" : 0,
      "timeUpdatingContentLessIndexes" : 2678829,
      "timeIndexingWithoutContent" : 0
    }, {
      "providerName" : "Library Maven: io.netty:netty:3.7.0.Final",
      "numberOfScannedFiles" : 836,
      "numberOfSkippedFiles" : 0,
      "numberOfFilesForIndexing" : 0,
      "numberOfFilesFullyIndexedByInfrastructureExtensions" : 0,
      "scanningTime" : 135830403,
      "timeProcessingUpToDateFiles" : 0,
      "timeUpdatingContentLessIndexes" : 3136151,
      "timeIndexingWithoutContent" : 0
    }, {
      "providerName" : "Library Maven: commons-net:commons-net:3.1",
      "numberOfScannedFiles" : 177,
      "numberOfSkippedFiles" : 0,
      "numberOfFilesForIndexing" : 0,
      "numberOfFilesFullyIndexedByInfrastructureExtensions" : 0,
      "scanningTime" : 130022968,
      "timeProcessingUpToDateFiles" : 0,
      "timeUpdatingContentLessIndexes" : 1050084,
      "timeIndexingWithoutContent" : 0
    }, {
      "providerName" : "Library Maven: commons-codec:commons-codec:1.4",
      "numberOfScannedFiles" : 35,
      "numberOfSkippedFiles" : 0,
      "numberOfFilesForIndexing" : 0,
      "numberOfFilesFullyIndexedByInfrastructureExtensions" : 0,
      "scanningTime" : 125967163,
      "timeProcessingUpToDateFiles" : 0,
      "timeUpdatingContentLessIndexes" : 648399,
      "timeIndexingWithoutContent" : 0
    }, {
      "providerName" : "Library Maven: org.apache.directory.server:apacheds-kerberos-codec:2.0.0-M15",
      "numberOfScannedFiles" : 482,
      "numberOfSkippedFiles" : 0,
      "numberOfFilesForIndexing" : 0,
      "numberOfFilesFullyIndexedByInfrastructureExtensions" : 0,
      "scanningTime" : 121402515,
      "timeProcessingUpToDateFiles" : 0,
      "timeUpdatingContentLessIndexes" : 2794039,
      "timeIndexingWithoutContent" : 0
    }, {
      "providerName" : "Library Maven: com.google.protobuf:protobuf-java:2.5.0",
      "numberOfScannedFiles" : 249,
      "numberOfSkippedFiles" : 0,
      "numberOfFilesForIndexing" : 0,
      "numberOfFilesFullyIndexedByInfrastructureExtensions" : 0,
      "scanningTime" : 117168784,
      "timeProcessingUpToDateFiles" : 0,
      "timeUpdatingContentLessIndexes" : 851384,
      "timeIndexingWithoutContent" : 0
    }, {
      "providerName" : "Library Maven: org.codehaus.jackson:jackson-core-asl:1.9.13",
      "numberOfScannedFiles" : 126,
      "numberOfSkippedFiles" : 0,
      "numberOfFilesForIndexing" : 0,
      "numberOfFilesFullyIndexedByInfrastructureExtensions" : 0,
      "scanningTime" : 110316262,
      "timeProcessingUpToDateFiles" : 0,
      "timeUpdatingContentLessIndexes" : 524806,
      "timeIndexingWithoutContent" : 0
    }, {
      "providerName" : "Library Maven: com.sun.jersey:jersey-core:1.9",
      "numberOfScannedFiles" : 356,
      "numberOfSkippedFiles" : 0,
      "numberOfFilesForIndexing" : 0,
      "numberOfFilesFullyIndexedByInfrastructureExtensions" : 0,
      "scanningTime" : 107548283,
      "timeProcessingUpToDateFiles" : 0,
      "timeUpdatingContentLessIndexes" : 1469882,
      "timeIndexingWithoutContent" : 0
    }, {
      "providerName" : "Library Maven: com.nimbusds:nimbus-jose-jwt:4.41.1",
      "numberOfScannedFiles" : 208,
      "numberOfSkippedFiles" : 0,
      "numberOfFilesForIndexing" : 0,
      "numberOfFilesFullyIndexedByInfrastructureExtensions" : 0,
      "scanningTime" : 103069754,
      "timeProcessingUpToDateFiles" : 0,
      "timeUpdatingContentLessIndexes" : 793291,
      "timeIndexingWithoutContent" : 0
    }, {
      "providerName" : "Library Maven: commons-cli:commons-cli:1.2",
      "numberOfScannedFiles" : 27,
      "numberOfSkippedFiles" : 0,
      "numberOfFilesForIndexing" : 0,
      "numberOfFilesFullyIndexedByInfrastructureExtensions" : 0,
      "scanningTime" : 102378181,
      "timeProcessingUpToDateFiles" : 0,
      "timeUpdatingContentLessIndexes" : 556839,
      "timeIndexingWithoutContent" : 0
    }, {
      "providerName" : "Library Maven: org.apache.zookeeper:zookeeper:3.4.6",
      "numberOfScannedFiles" : 442,
      "numberOfSkippedFiles" : 0,
      "numberOfFilesForIndexing" : 0,
      "numberOfFilesFullyIndexedByInfrastructureExtensions" : 0,
      "scanningTime" : 101205012,
      "timeProcessingUpToDateFiles" : 0,
      "timeUpdatingContentLessIndexes" : 1601197,
      "timeIndexingWithoutContent" : 0
    }, {
      "providerName" : "Library Maven: net.java.dev.jets3t:jets3t:0.9.0",
      "numberOfScannedFiles" : 314,
      "numberOfSkippedFiles" : 0,
      "numberOfFilesForIndexing" : 0,
      "numberOfFilesFullyIndexedByInfrastructureExtensions" : 0,
      "scanningTime" : 100729080,
      "timeProcessingUpToDateFiles" : 0,
      "timeUpdatingContentLessIndexes" : 1396590,
      "timeIndexingWithoutContent" : 0
    }, {
      "providerName" : "Library Maven: org.apache.hadoop:hadoop-annotations:2.8.5",
      "numberOfScannedFiles" : 21,
      "numberOfSkippedFiles" : 0,
      "numberOfFilesForIndexing" : 0,
      "numberOfFilesFullyIndexedByInfrastructureExtensions" : 0,
      "scanningTime" : 98469040,
      "timeProcessingUpToDateFiles" : 0,
      "timeUpdatingContentLessIndexes" : 580332,
      "timeIndexingWithoutContent" : 0
    }, {
      "providerName" : "Library Maven: com.google.code.gson:gson:2.2.4",
      "numberOfScannedFiles" : 154,
      "numberOfSkippedFiles" : 0,
      "numberOfFilesForIndexing" : 0,
      "numberOfFilesFullyIndexedByInfrastructureExtensions" : 0,
      "scanningTime" : 88608059,
      "timeProcessingUpToDateFiles" : 0,
      "timeUpdatingContentLessIndexes" : 532243,
      "timeIndexingWithoutContent" : 0
    }, {
      "providerName" : "Library Maven: xmlenc:xmlenc:0.52",
      "numberOfScannedFiles" : 12,
      "numberOfSkippedFiles" : 0,
      "numberOfFilesForIndexing" : 0,
      "numberOfFilesFullyIndexedByInfrastructureExtensions" : 0,
      "scanningTime" : 86511472,
      "timeProcessingUpToDateFiles" : 0,
      "timeUpdatingContentLessIndexes" : 606353,
      "timeIndexingWithoutContent" : 0
    }, {
      "providerName" : "Library Maven: javax.servlet:servlet-api:2.5",
      "numberOfScannedFiles" : 63,
      "numberOfSkippedFiles" : 0,
      "numberOfFilesForIndexing" : 0,
      "numberOfFilesFullyIndexedByInfrastructureExtensions" : 0,
      "scanningTime" : 77551910,
      "timeProcessingUpToDateFiles" : 0,
      "timeUpdatingContentLessIndexes" : 1175283,
      "timeIndexingWithoutContent" : 0
    }, {
      "providerName" : "Library Maven: commons-beanutils:commons-beanutils-core:1.8.0",
      "numberOfScannedFiles" : 121,
      "numberOfSkippedFiles" : 0,
      "numberOfFilesForIndexing" : 0,
      "numberOfFilesFullyIndexedByInfrastructureExtensions" : 0,
      "scanningTime" : 76926769,
      "timeProcessingUpToDateFiles" : 0,
      "timeUpdatingContentLessIndexes" : 465014,
      "timeIndexingWithoutContent" : 0
    }, {
      "providerName" : "Library Maven: commons-configuration:commons-configuration:1.6",
      "numberOfScannedFiles" : 173,
      "numberOfSkippedFiles" : 0,
      "numberOfFilesForIndexing" : 0,
      "numberOfFilesFullyIndexedByInfrastructureExtensions" : 0,
      "scanningTime" : 75649744,
      "timeProcessingUpToDateFiles" : 0,
      "timeUpdatingContentLessIndexes" : 780642,
      "timeIndexingWithoutContent" : 0
    }, {
      "providerName" : "Library Maven: org.mortbay.jetty:jetty:6.1.26",
      "numberOfScannedFiles" : 246,
      "numberOfSkippedFiles" : 0,
      "numberOfFilesForIndexing" : 0,
      "numberOfFilesFullyIndexedByInfrastructureExtensions" : 0,
      "scanningTime" : 74093792,
      "timeProcessingUpToDateFiles" : 0,
      "timeUpdatingContentLessIndexes" : 982602,
      "timeIndexingWithoutContent" : 0
    }, {
      "providerName" : "Library Maven: log4j:log4j:1.2.17",
      "numberOfScannedFiles" : 324,
      "numberOfSkippedFiles" : 0,
      "numberOfFilesForIndexing" : 0,
      "numberOfFilesFullyIndexedByInfrastructureExtensions" : 0,
      "scanningTime" : 73847624,
      "timeProcessingUpToDateFiles" : 0,
      "timeUpdatingContentLessIndexes" : 2779146,
      "timeIndexingWithoutContent" : 0
    }, {
      "providerName" : "Library Maven: net.minidev:json-smart:2.3",
      "numberOfScannedFiles" : 95,
      "numberOfSkippedFiles" : 0,
      "numberOfFilesForIndexing" : 0,
      "numberOfFilesFullyIndexedByInfrastructureExtensions" : 0,
      "scanningTime" : 67239607,
      "timeProcessingUpToDateFiles" : 0,
      "timeUpdatingContentLessIndexes" : 383159,
      "timeIndexingWithoutContent" : 0
    }, {
      "providerName" : "Indexable set contributor 'com.intellij.javaee.ExternalResourcesRootsProvider@48080808' (non-project)",
      "numberOfScannedFiles" : 222,
      "numberOfSkippedFiles" : 4,
      "numberOfFilesForIndexing" : 0,
      "numberOfFilesFullyIndexedByInfrastructureExtensions" : 0,
      "scanningTime" : 64358729,
      "timeProcessingUpToDateFiles" : 0,
      "timeUpdatingContentLessIndexes" : 906233,
      "timeIndexingWithoutContent" : 0
    }, {
      "providerName" : "Library Maven: org.slf4j:slf4j-api:1.7.10",
      "numberOfScannedFiles" : 31,
      "numberOfSkippedFiles" : 0,
      "numberOfFilesForIndexing" : 0,
      "numberOfFilesFullyIndexedByInfrastructureExtensions" : 0,
      "scanningTime" : 60066869,
      "timeProcessingUpToDateFiles" : 0,
      "timeUpdatingContentLessIndexes" : 143674,
      "timeIndexingWithoutContent" : 0
    }, {
      "providerName" : "Library Maven: commons-beanutils:commons-beanutils:1.7.0",
      "numberOfScannedFiles" : 120,
      "numberOfSkippedFiles" : 0,
      "numberOfFilesForIndexing" : 0,
      "numberOfFilesFullyIndexedByInfrastructureExtensions" : 0,
      "scanningTime" : 47537838,
      "timeProcessingUpToDateFiles" : 0,
      "timeUpdatingContentLessIndexes" : 486340,
      "timeIndexingWithoutContent" : 0
    }, {
      "providerName" : "Library Maven: org.apache.commons:commons-compress:1.4.1",
      "numberOfScannedFiles" : 134,
      "numberOfSkippedFiles" : 0,
      "numberOfFilesForIndexing" : 0,
      "numberOfFilesFullyIndexedByInfrastructureExtensions" : 0,
      "scanningTime" : 46850707,
      "timeProcessingUpToDateFiles" : 0,
      "timeUpdatingContentLessIndexes" : 642656,
      "timeIndexingWithoutContent" : 0
    }, {
      "providerName" : "Library Maven: net.minidev:accessors-smart:1.2",
      "numberOfScannedFiles" : 16,
      "numberOfSkippedFiles" : 0,
      "numberOfFilesForIndexing" : 0,
      "numberOfFilesFullyIndexedByInfrastructureExtensions" : 0,
      "scanningTime" : 43200547,
      "timeProcessingUpToDateFiles" : 0,
      "timeUpdatingContentLessIndexes" : 125329,
      "timeIndexingWithoutContent" : 0
    }, {
      "providerName" : "Library Maven: commons-lang:commons-lang:2.6",
      "numberOfScannedFiles" : 138,
      "numberOfSkippedFiles" : 0,
      "numberOfFilesForIndexing" : 0,
      "numberOfFilesFullyIndexedByInfrastructureExtensions" : 0,
      "scanningTime" : 40704643,
      "timeProcessingUpToDateFiles" : 0,
      "timeUpdatingContentLessIndexes" : 627163,
      "timeIndexingWithoutContent" : 0
    }, {
      "providerName" : "Library Maven: org.apache.curator:curator-recipes:2.7.1",
      "numberOfScannedFiles" : 209,
      "numberOfSkippedFiles" : 0,
      "numberOfFilesForIndexing" : 0,
      "numberOfFilesFullyIndexedByInfrastructureExtensions" : 0,
      "scanningTime" : 36766670,
      "timeProcessingUpToDateFiles" : 0,
      "timeUpdatingContentLessIndexes" : 784922,
      "timeIndexingWithoutContent" : 0
    }, {
      "providerName" : "Library Maven: javax.xml.bind:jaxb-api:2.2.2",
      "numberOfScannedFiles" : 106,
      "numberOfSkippedFiles" : 0,
      "numberOfFilesForIndexing" : 0,
      "numberOfFilesFullyIndexedByInfrastructureExtensions" : 0,
      "scanningTime" : 36211229,
      "timeProcessingUpToDateFiles" : 0,
      "timeUpdatingContentLessIndexes" : 530949,
      "timeIndexingWithoutContent" : 0
    }, {
      "providerName" : "Library Maven: org.tukaani:xz:1.0",
      "numberOfScannedFiles" : 103,
      "numberOfSkippedFiles" : 0,
      "numberOfFilesForIndexing" : 0,
      "numberOfFilesFullyIndexedByInfrastructureExtensions" : 0,
      "scanningTime" : 33727517,
      "timeProcessingUpToDateFiles" : 0,
      "timeUpdatingContentLessIndexes" : 371324,
      "timeIndexingWithoutContent" : 0
    }, {
      "providerName" : "Library Maven: com.jcraft:jsch:0.1.54",
      "numberOfScannedFiles" : 167,
      "numberOfSkippedFiles" : 0,
      "numberOfFilesForIndexing" : 0,
      "numberOfFilesFullyIndexedByInfrastructureExtensions" : 0,
      "scanningTime" : 33137058,
      "timeProcessingUpToDateFiles" : 0,
      "timeUpdatingContentLessIndexes" : 560213,
      "timeIndexingWithoutContent" : 0
    }, {
      "providerName" : "Library Maven: org.apache.curator:curator-framework:2.7.1",
      "numberOfScannedFiles" : 174,
      "numberOfSkippedFiles" : 0,
      "numberOfFilesForIndexing" : 0,
      "numberOfFilesFullyIndexedByInfrastructureExtensions" : 0,
      "scanningTime" : 30748899,
      "timeProcessingUpToDateFiles" : 0,
      "timeUpdatingContentLessIndexes" : 591804,
      "timeIndexingWithoutContent" : 0
    }, {
      "providerName" : "Library Maven: org.mortbay.jetty:jetty-util:6.1.26",
      "numberOfScannedFiles" : 108,
      "numberOfSkippedFiles" : 0,
      "numberOfFilesForIndexing" : 0,
      "numberOfFilesFullyIndexedByInfrastructureExtensions" : 0,
      "scanningTime" : 27771494,
      "timeProcessingUpToDateFiles" : 0,
      "timeUpdatingContentLessIndexes" : 379828,
      "timeIndexingWithoutContent" : 0
    }, {
      "providerName" : "Library Maven: javax.xml.stream:stax-api:1.0-2",
      "numberOfScannedFiles" : 38,
      "numberOfSkippedFiles" : 0,
      "numberOfFilesForIndexing" : 0,
      "numberOfFilesFullyIndexedByInfrastructureExtensions" : 0,
      "scanningTime" : 22859647,
      "timeProcessingUpToDateFiles" : 0,
      "timeUpdatingContentLessIndexes" : 143304,
      "timeIndexingWithoutContent" : 0
    }, {
      "providerName" : "Library Maven: javax.activation:activation:1.1",
      "numberOfScannedFiles" : 42,
      "numberOfSkippedFiles" : 0,
      "numberOfFilesForIndexing" : 0,
      "numberOfFilesFullyIndexedByInfrastructureExtensions" : 0,
      "scanningTime" : 21527160,
      "timeProcessingUpToDateFiles" : 0,
      "timeUpdatingContentLessIndexes" : 160260,
      "timeIndexingWithoutContent" : 0
    }, {
      "providerName" : "Library Maven: commons-digester:commons-digester:1.8",
      "numberOfScannedFiles" : 104,
      "numberOfSkippedFiles" : 0,
      "numberOfFilesForIndexing" : 0,
      "numberOfFilesFullyIndexedByInfrastructureExtensions" : 0,
      "scanningTime" : 17772443,
      "timeProcessingUpToDateFiles" : 0,
      "timeUpdatingContentLessIndexes" : 415135,
      "timeIndexingWithoutContent" : 0
    }, {
      "providerName" : "Library Maven: com.google.code.findbugs:jsr305:3.0.0",
      "numberOfScannedFiles" : 67,
      "numberOfSkippedFiles" : 0,
      "numberOfFilesForIndexing" : 0,
      "numberOfFilesFullyIndexedByInfrastructureExtensions" : 0,
      "scanningTime" : 17712229,
      "timeProcessingUpToDateFiles" : 0,
      "timeUpdatingContentLessIndexes" : 237196,
      "timeIndexingWithoutContent" : 0
    }, {
      "providerName" : "Library Maven: javax.servlet.jsp:jsp-api:2.1",
      "numberOfScannedFiles" : 93,
      "numberOfSkippedFiles" : 0,
      "numberOfFilesForIndexing" : 0,
      "numberOfFilesFullyIndexedByInfrastructureExtensions" : 0,
      "scanningTime" : 15991244,
      "timeProcessingUpToDateFiles" : 0,
      "timeUpdatingContentLessIndexes" : 357980,
      "timeIndexingWithoutContent" : 0
    }, {
      "providerName" : "Library Maven: com.sun.jersey:jersey-json:1.9",
      "numberOfScannedFiles" : 99,
      "numberOfSkippedFiles" : 0,
      "numberOfFilesForIndexing" : 0,
      "numberOfFilesFullyIndexedByInfrastructureExtensions" : 0,
      "scanningTime" : 15107855,
      "timeProcessingUpToDateFiles" : 0,
      "timeUpdatingContentLessIndexes" : 321805,
      "timeIndexingWithoutContent" : 0
    }, {
      "providerName" : "Library Maven: org.apache.hadoop:hadoop-auth:2.8.5",
      "numberOfScannedFiles" : 53,
      "numberOfSkippedFiles" : 0,
      "numberOfFilesForIndexing" : 0,
      "numberOfFilesFullyIndexedByInfrastructureExtensions" : 0,
      "scanningTime" : 12334670,
      "timeProcessingUpToDateFiles" : 0,
      "timeUpdatingContentLessIndexes" : 164031,
      "timeIndexingWithoutContent" : 0
    }, {
      "providerName" : "Library Maven: org.apache.curator:curator-client:2.7.1",
      "numberOfScannedFiles" : 62,
      "numberOfSkippedFiles" : 0,
      "numberOfFilesForIndexing" : 0,
      "numberOfFilesFullyIndexedByInfrastructureExtensions" : 0,
      "scanningTime" : 10239192,
      "timeProcessingUpToDateFiles" : 0,
      "timeUpdatingContentLessIndexes" : 222993,
      "timeIndexingWithoutContent" : 0
    }, {
      "providerName" : "Library Maven: org.codehaus.jettison:jettison:1.1",
      "numberOfScannedFiles" : 44,
      "numberOfSkippedFiles" : 0,
      "numberOfFilesForIndexing" : 0,
      "numberOfFilesFullyIndexedByInfrastructureExtensions" : 0,
      "scanningTime" : 9716650,
      "timeProcessingUpToDateFiles" : 0,
      "timeUpdatingContentLessIndexes" : 156124,
      "timeIndexingWithoutContent" : 0
    }, {
      "providerName" : "Library Maven: commons-logging:commons-logging:1.1.3",
      "numberOfScannedFiles" : 33,
      "numberOfSkippedFiles" : 0,
      "numberOfFilesForIndexing" : 0,
      "numberOfFilesFullyIndexedByInfrastructureExtensions" : 0,
      "scanningTime" : 8101356,
      "timeProcessingUpToDateFiles" : 0,
      "timeUpdatingContentLessIndexes" : 116351,
      "timeIndexingWithoutContent" : 0
    }, {
      "providerName" : "Library Maven: org.apache.directory.api:api-util:1.0.0-M20",
      "numberOfScannedFiles" : 48,
      "numberOfSkippedFiles" : 0,
      "numberOfFilesForIndexing" : 0,
      "numberOfFilesFullyIndexedByInfrastructureExtensions" : 0,
      "scanningTime" : 7679535,
      "timeProcessingUpToDateFiles" : 0,
      "timeUpdatingContentLessIndexes" : 217165,
      "timeIndexingWithoutContent" : 0
    }, {
      "providerName" : "Library Maven: com.thoughtworks.paranamer:paranamer:2.3",
      "numberOfScannedFiles" : 18,
      "numberOfSkippedFiles" : 0,
      "numberOfFilesForIndexing" : 0,
      "numberOfFilesFullyIndexedByInfrastructureExtensions" : 0,
      "scanningTime" : 6034626,
      "timeProcessingUpToDateFiles" : 0,
      "timeUpdatingContentLessIndexes" : 65616,
      "timeIndexingWithoutContent" : 0
    }, {
      "providerName" : "Library Maven: org.apache.directory.server:apacheds-i18n:2.0.0-M15",
      "numberOfScannedFiles" : 11,
      "numberOfSkippedFiles" : 0,
      "numberOfFilesForIndexing" : 0,
      "numberOfFilesFullyIndexedByInfrastructureExtensions" : 0,
      "scanningTime" : 5850627,
      "timeProcessingUpToDateFiles" : 0,
      "timeUpdatingContentLessIndexes" : 40198,
      "timeIndexingWithoutContent" : 0
    }, {
      "providerName" : "Library Maven: org.xerial.snappy:snappy-java:1.0.4.1",
      "numberOfScannedFiles" : 25,
      "numberOfSkippedFiles" : 0,
      "numberOfFilesForIndexing" : 0,
      "numberOfFilesFullyIndexedByInfrastructureExtensions" : 0,
      "scanningTime" : 4636088,
      "timeProcessingUpToDateFiles" : 0,
      "timeUpdatingContentLessIndexes" : 88368,
      "timeIndexingWithoutContent" : 0
    }, {
      "providerName" : "Library Maven: asm:asm:3.1",
      "numberOfScannedFiles" : 24,
      "numberOfSkippedFiles" : 0,
      "numberOfFilesForIndexing" : 0,
      "numberOfFilesFullyIndexedByInfrastructureExtensions" : 0,
      "scanningTime" : 3684053,
      "timeProcessingUpToDateFiles" : 0,
      "timeUpdatingContentLessIndexes" : 89552,
      "timeIndexingWithoutContent" : 0
    }, {
      "providerName" : "Library Maven: org.apache.directory.api:api-asn1-api:1.0.0-M20",
      "numberOfScannedFiles" : 13,
      "numberOfSkippedFiles" : 0,
      "numberOfFilesForIndexing" : 0,
      "numberOfFilesFullyIndexedByInfrastructureExtensions" : 0,
      "scanningTime" : 3492148,
      "timeProcessingUpToDateFiles" : 0,
      "timeUpdatingContentLessIndexes" : 42787,
      "timeIndexingWithoutContent" : 0
    }, {
      "providerName" : "Library Maven: org.mortbay.jetty:jetty-sslengine:6.1.26",
      "numberOfScannedFiles" : 8,
      "numberOfSkippedFiles" : 0,
      "numberOfFilesForIndexing" : 0,
      "numberOfFilesFullyIndexedByInfrastructureExtensions" : 0,
      "scanningTime" : 3213414,
      "timeProcessingUpToDateFiles" : 0,
      "timeUpdatingContentLessIndexes" : 30279,
      "timeIndexingWithoutContent" : 0
    }, {
      "providerName" : "Library Maven: org.ow2.asm:asm:5.0.4",
      "numberOfScannedFiles" : 26,
      "numberOfSkippedFiles" : 0,
      "numberOfFilesForIndexing" : 0,
      "numberOfFilesFullyIndexedByInfrastructureExtensions" : 0,
      "scanningTime" : 3191681,
      "timeProcessingUpToDateFiles" : 0,
      "timeUpdatingContentLessIndexes" : 87161,
      "timeIndexingWithoutContent" : 0
    }, {
      "providerName" : "Library Maven: org.slf4j:slf4j-log4j12:1.7.10",
      "numberOfScannedFiles" : 9,
      "numberOfSkippedFiles" : 0,
      "numberOfFilesForIndexing" : 0,
      "numberOfFilesFullyIndexedByInfrastructureExtensions" : 0,
      "scanningTime" : 2909878,
      "timeProcessingUpToDateFiles" : 0,
      "timeUpdatingContentLessIndexes" : 53596,
      "timeIndexingWithoutContent" : 0
    }, {
      "providerName" : "Library Maven: org.codehaus.jackson:jackson-xc:1.8.3",
      "numberOfScannedFiles" : 17,
      "numberOfSkippedFiles" : 0,
      "numberOfFilesForIndexing" : 0,
      "numberOfFilesFullyIndexedByInfrastructureExtensions" : 0,
      "scanningTime" : 2677851,
      "timeProcessingUpToDateFiles" : 0,
      "timeUpdatingContentLessIndexes" : 76083,
      "timeIndexingWithoutContent" : 0
    }, {
      "providerName" : "Library Maven: com.github.stephenc.jcip:jcip-annotations:1.0-1",
      "numberOfScannedFiles" : 7,
      "numberOfSkippedFiles" : 0,
      "numberOfFilesForIndexing" : 0,
      "numberOfFilesFullyIndexedByInfrastructureExtensions" : 0,
      "scanningTime" : 2441422,
      "timeProcessingUpToDateFiles" : 0,
      "timeUpdatingContentLessIndexes" : 21493,
      "timeIndexingWithoutContent" : 0
    }, {
      "providerName" : "Library Maven: org.codehaus.jackson:jackson-jaxrs:1.8.3",
      "numberOfScannedFiles" : 13,
      "numberOfSkippedFiles" : 0,
      "numberOfFilesForIndexing" : 0,
      "numberOfFilesFullyIndexedByInfrastructureExtensions" : 0,
      "scanningTime" : 2290193,
      "timeProcessingUpToDateFiles" : 0,
      "timeUpdatingContentLessIndexes" : 48328,
      "timeIndexingWithoutContent" : 0
    }, {
      "providerName" : "Library Maven: com.jamesmurty.utils:java-xmlbuilder:0.4",
      "numberOfScannedFiles" : 7,
      "numberOfSkippedFiles" : 0,
      "numberOfFilesForIndexing" : 0,
      "numberOfFilesFullyIndexedByInfrastructureExtensions" : 0,
      "scanningTime" : 1676318,
      "timeProcessingUpToDateFiles" : 0,
      "timeUpdatingContentLessIndexes" : 26372,
      "timeIndexingWithoutContent" : 0
    }, {
      "providerName" : "Indexable set contributor 'Scratches & Consoles' (project)",
      "numberOfScannedFiles" : 0,
      "numberOfSkippedFiles" : 0,
      "numberOfFilesForIndexing" : 0,
      "numberOfFilesFullyIndexedByInfrastructureExtensions" : 0,
      "scanningTime" : 0,
      "timeProcessingUpToDateFiles" : 0,
      "timeUpdatingContentLessIndexes" : 0,
      "timeIndexingWithoutContent" : 0
    }, {
      "providerName" : "Indexable set contributor 'Scratches & Consoles' (non-project)",
      "numberOfScannedFiles" : 0,
      "numberOfSkippedFiles" : 0,
      "numberOfFilesForIndexing" : 0,
      "numberOfFilesFullyIndexedByInfrastructureExtensions" : 0,
      "scanningTime" : 0,
      "timeProcessingUpToDateFiles" : 0,
      "timeUpdatingContentLessIndexes" : 0,
      "timeIndexingWithoutContent" : 0
    }, {
      "providerName" : "Indexable set contributor 'com.intellij.javaee.ExternalResourcesRootsProvider@48080808' (project)",
      "numberOfScannedFiles" : 0,
      "numberOfSkippedFiles" : 0,
      "numberOfFilesForIndexing" : 0,
      "numberOfFilesFullyIndexedByInfrastructureExtensions" : 0,
      "scanningTime" : 0,
      "timeProcessingUpToDateFiles" : 0,
      "timeUpdatingContentLessIndexes" : 0,
      "timeIndexingWithoutContent" : 0
    }, {
      "providerName" : "Indexable set contributor 'Kotlin Script dependencies' (non-project)",
      "numberOfScannedFiles" : 0,
      "numberOfSkippedFiles" : 0,
      "numberOfFilesForIndexing" : 0,
      "numberOfFilesFullyIndexedByInfrastructureExtensions" : 0,
      "scanningTime" : 0,
      "timeProcessingUpToDateFiles" : 0,
      "timeUpdatingContentLessIndexes" : 0,
      "timeIndexingWithoutContent" : 0
    }, {
      "providerName" : "Indexable set contributor 'Kotlin Script dependencies' (project)",
      "numberOfScannedFiles" : 0,
      "numberOfSkippedFiles" : 0,
      "numberOfFilesForIndexing" : 0,
      "numberOfFilesFullyIndexedByInfrastructureExtensions" : 0,
      "scanningTime" : 0,
      "timeProcessingUpToDateFiles" : 0,
      "timeUpdatingContentLessIndexes" : 0,
      "timeIndexingWithoutContent" : 0
    } ],
    "fileProviderStatistics" : [ ]
  }
}